odoc/__init__.py
odoc/calc.py
odoc/calc_manifest.py
odoc/calc_meta.py
odoc/calc_ranges.py
odoc/calc_settings.py
odoc/calc_sheet.py
odoc/calc_styles.py
odoc/calc_util.py
odoc/odoc_attr_checker.py
odoc/odoc_xml.py
odoc/version.py
odoc-0.7.0b1.dist-info/METADATA
odoc-0.7.0b1.dist-info/WHEEL
odoc-0.7.0b1.dist-info/licenses/LICENSE
odoc-0.7.0b1.dist-info/RECORD
