Metadata-Version: 2.4
Name: odoc
Version: 0.7.0b1
Summary: An OpenDocument Spreadsheet Generator
Project-URL: Homepage, https://codeberg.org/odoc/odoc
Project-URL: Repository, https://codeberg.org/odoc/odoc.git
Project-URL: Issues, https://codeberg.org/odoc/odoc/issues
Project-URL: Documentation, https://codeberg.org/odoc/odoc/src/branch/main/examples
Author-email: odoc <odoc@tutamail.com>
License-Expression: MIT
License-File: LICENSE
Keywords: libreoffice,ods,opendocument,spreadsheet
Classifier: Development Status :: 4 - Beta
Classifier: Intended Audience :: Developers
Classifier: Operating System :: OS Independent
Classifier: Programming Language :: Python :: 3
Classifier: Topic :: Office/Business :: Financial :: Spreadsheet
Requires-Python: >=3.11
